dbt_cloud_jobs/dbt_api_helpers.py
dbt_cloud_jobs/exceptions.py
dbt_cloud_jobs/logger.py
dbt_cloud_jobs/main.py
dbt_cloud_jobs/parser.py
dbt_cloud_jobs/sync_job.py
dbt_cloud_jobs/utils.py
dbt_cloud_jobs/validator.py
dbt_cloud_jobs/version.py
dbt_cloud_jobs-0.2.0.dist-info/LICENSE
dbt_cloud_jobs-0.2.0.dist-info/METADATA
dbt_cloud_jobs-0.2.0.dist-info/WHEEL
dbt_cloud_jobs-0.2.0.dist-info/entry_points.txt
dbt_cloud_jobs-0.2.0.dist-info/RECORD
