Metadata-Version: 2.3
Name: dbt-cloud-jobs
Version: 0.2.0
Summary: Version control your dbt Cloud jobs with YML.
License: MIT
Keywords: python,cli,dbt,CI/CD
Author: Padraic Slattery
Author-email: pgoslatara@gmail.com
Maintainer: Padraic Slattery
Maintainer-email: pgoslatara@gmail.com
Requires-Python: >=3.9,<3.13
Classifier: Programming Language :: Python
Classifier: Programming Language :: Python :: 3
Classifier: Programming Language :: Python :: 3 :: Only
Classifier: Programming Language :: Python :: 3.9
Classifier: Programming Language :: Python :: 3.10
Classifier: Programming Language :: Python :: 3.11
Classifier: Programming Language :: Python :: 3.12
Requires-Dist: pydantic (>=2)
Requires-Dist: pyyaml
Requires-Dist: requests
